pyanyzip/__init__.py
pyanyzip/core.py
pyanyzip/static.py
pyanyzip-0.0.24.dist-info/METADATA
pyanyzip-0.0.24.dist-info/WHEEL
pyanyzip-0.0.24.dist-info/licenses/LICENSE
pyanyzip-0.0.24.dist-info/RECORD
