Metadata-Version: 2.4
Name: pyanyzip
Version: 0.0.24
Summary: pyanyzip is a module to help with dealing with compressed files transparently
Project-URL: Homepage, https://github.com/veltzer/pyanyzip
Project-URL: Bug Tracker, https://github.com/veltzer/pyanyzip/issues
Project-URL: Documentation, https://veltzer.github.io/pyanyzip
Project-URL: Download, https://pypi.org/project/pyanyzip/
Project-URL: Repository, https://github.com/veltzer/pyanyzip
Author-email: Mark Veltzer <mark.veltzer@gmail.com>
Maintainer-email: Mark Veltzer <mark.veltzer@gmail.com>
License-Expression: MIT
License-File: LICENSE
Keywords: bz2,gzip,python,zip
Classifier: Development Status :: 4 - Beta
Classifier: Environment :: Console
Classifier: License :: OSI Approved :: MIT License
Classifier: Operating System :: OS Independent
Classifier: Programming Language :: Python
Classifier: Programming Language :: Python :: 3
Classifier: Programming Language :: Python :: 3 :: Only
Classifier: Programming Language :: Python :: 3.12
Classifier: Topic :: Utilities
Requires-Python: >=3.12
Requires-Dist: pypipegzip
